main/__init__.py
main/main.py
Dumbdans_Adventure-0.0.2.dist-info/LICENSE.md
Dumbdans_Adventure-0.0.2.dist-info/METADATA
Dumbdans_Adventure-0.0.2.dist-info/WHEEL
Dumbdans_Adventure-0.0.2.dist-info/top_level.txt
Dumbdans_Adventure-0.0.2.dist-info/RECORD
