Metadata-Version: 2.1
Name: Dumbdans-Adventure
Version: 0.0.2
Summary: Arcade game made with pygame
Home-page: https://github.com/AlefAdonis/Dumbdan-Game
Author: Álef Ádonis
Author-email: alef.carlos@ccc.ufcg.edu.br
License: UNKNOWN
Platform: UNKNOWN
Classifier: Programming Language :: Python :: 3
Classifier: License :: OSI Approved :: MIT License
Classifier: Operating System :: OS Independent
Requires-Python: >=3.6
